README.md
setup.cfg
setup.py
choice_sort_package/__init__.py
choice_sort_package/__main__.py
choice_sort_package/choice_sort.py
choice_sort_package/input_check.py
choice_sort_package.egg-info/PKG-INFO
choice_sort_package.egg-info/SOURCES.txt
choice_sort_package.egg-info/dependency_links.txt
choice_sort_package.egg-info/requires.txt
choice_sort_package.egg-info/top_level.txt