Metadata-Version: 2.1
Name: choice-sort-package
Version: 1.0
Summary: Модуль, проводящий сортировку выбором
License: MIT
